emildecoster/__init__.py
emildecoster/__main__.py
emildecoster/cli.py
emildecoster/frac.py
emildecoster/mypackages.py
emildecoster-0.0.2.dist-info/AUTHORS.rst
emildecoster-0.0.2.dist-info/METADATA
emildecoster-0.0.2.dist-info/WHEEL
emildecoster-0.0.2.dist-info/entry_points.txt
emildecoster-0.0.2.dist-info/top_level.txt
emildecoster-0.0.2.dist-info/RECORD
