Metadata-Version: 2.1
Name: emildecoster
Version: 0.0.2
Summary: This is my first package!
Home-page: https://github.com/Emil-Decoster/python-emildecoster
Author: Emil Decoster
Author-email: emildecoster@gmail.com
License: UNKNOWN
Project-URL: Issue Tracker, https://github.com/Emil-Decoster/python-emildecoster/issues
Project-URL: Documentation, https://python-emildecoster.readthedocs.io/
Project-URL: Changelog, https://python-emildecoster.readthedocs.io/en/latest/changelog.html
Platform: UNKNOWN
Classifier: Development Status :: 5 - Production/Stable
Classifier: Intended Audience :: Developers
Classifier: Operating System :: Unix
Classifier: Operating System :: POSIX
Classifier: Operating System :: Microsoft :: Windows
Classifier: Programming Language :: Python
Classifier: Programming Language :: Python :: 2.7
Classifier: Programming Language :: Python :: 3
Classifier: Programming Language :: Python :: 3.5
Classifier: Programming Language :: Python :: 3.6
Classifier: Programming Language :: Python :: 3.7
Classifier: Programming Language :: Python :: 3.8
Classifier: Programming Language :: Python :: Implementation :: CPython
Classifier: Programming Language :: Python :: Implementation :: PyPy
Classifier: Topic :: Utilities
Requires-Python: >=2.7, !=3.0.*, !=3.1.*, !=3.2.*, !=3.3.*, !=3.4.*
